bryson/__init__.py
bryson/utils/welcome.py
example_pkg/__init__.py
bryson-0.0.8.dist-info/LICENSE
bryson-0.0.8.dist-info/METADATA
bryson-0.0.8.dist-info/WHEEL
bryson-0.0.8.dist-info/top_level.txt
bryson-0.0.8.dist-info/RECORD
