Metadata-Version: 2.1
Name: bryson
Version: 0.0.8
Summary: A package using various blockchains to generate a random number
Home-page: http://bryson.studio/
Author: Jonathan Zavialov
Author-email: jonzavialov@gmail.com
License: UNKNOWN
Platform: UNKNOWN
Classifier: Programming Language :: Python :: 3
Classifier: License :: OSI Approved :: MIT License
Classifier: Operating System :: OS Independent
Requires-Python: >=3.6
Requires-Dist: requests
